tempyrature/__init__.py
tempyrature/tempyrature.py
tempyrature-1.0.2.dist-info/LICENSE
tempyrature-1.0.2.dist-info/METADATA
tempyrature-1.0.2.dist-info/WHEEL
tempyrature-1.0.2.dist-info/top_level.txt
tempyrature-1.0.2.dist-info/RECORD
